MANIFEST.in
README.md
setup.cfg
setup.py
pimaton/Pimaton.py
pimaton/PimatonCam.py
pimaton/PimatonExceptions.py
pimaton/PimatonGUI.py
pimaton/PimatonGUITK.py
pimaton/PimatonImage.py
pimaton/PimatonPrint.py
pimaton/PimatonTUI.py
pimaton/PimatonUI.py
pimaton/Singleton.py
pimaton/__init__.py
pimaton/_version.py
pimaton.egg-info/PKG-INFO
pimaton.egg-info/SOURCES.txt
pimaton.egg-info/dependency_links.txt
pimaton.egg-info/entry_points.txt
pimaton.egg-info/not-zip-safe
pimaton.egg-info/requires.txt
pimaton.egg-info/top_level.txt
pimaton/assets/default_config.yaml
pimaton/assets/default_config_full.yaml