Metadata-Version: 1.1
Name: pimaton
Version: 0.0.4
Summary: A photobooth application for raspberry pi
Home-page: https://github.com/bacardi55/pimaton
Author: bacardi55
Author-email: bac@rdi55.pl
License: GPLv3
Download-URL: https://github.com/bacardi55/pimaton/archive/v0.0.4.tar.gz
Keywords: photobooth raspberrypi picamera
Platform: UNKNOWN
Classifier: Development Status :: 4 - Beta
Classifier: Environment :: Console
Classifier: Environment :: X11 Applications
Classifier: Intended Audience :: Developers
Classifier: License :: OSI Approved :: GNU General Public License v3 or later (GPLv3+)
Classifier: Operating System :: POSIX :: Linux
Classifier: Programming Language :: Python :: 2
Classifier: Programming Language :: Python :: 2.7
